odoo/addons/email_template_configurator/README.rst
odoo/addons/email_template_configurator/__init__.py
odoo/addons/email_template_configurator/__manifest__.py
odoo/addons/email_template_configurator/i18n/email_template_configurator.pot
odoo/addons/email_template_configurator/i18n/it.po
odoo/addons/email_template_configurator/models/__init__.py
odoo/addons/email_template_configurator/models/email_template_placeholder.py
odoo/addons/email_template_configurator/models/mail_template.py
odoo/addons/email_template_configurator/readme/CONFIGURATION.rst
odoo/addons/email_template_configurator/readme/CONTRIBUTORS.rst
odoo/addons/email_template_configurator/readme/DESCRIPTION.rst
odoo/addons/email_template_configurator/readme/USAGE.rst
odoo/addons/email_template_configurator/security/email_template_placeholder.xml
odoo/addons/email_template_configurator/security/groups.xml
odoo/addons/email_template_configurator/static/description/icon.png
odoo/addons/email_template_configurator/static/description/index.html
odoo/addons/email_template_configurator/tests/__init__.py
odoo/addons/email_template_configurator/tests/test_configurator.py
odoo/addons/email_template_configurator/views/email_template_placeholder.xml
odoo/addons/email_template_configurator/views/mail_template.xml
odoo14_addon_email_template_configurator-14.0.1.0.2.dev4.dist-info/METADATA
odoo14_addon_email_template_configurator-14.0.1.0.2.dev4.dist-info/WHEEL
odoo14_addon_email_template_configurator-14.0.1.0.2.dev4.dist-info/top_level.txt
odoo14_addon_email_template_configurator-14.0.1.0.2.dev4.dist-info/RECORD
