Metadata-Version: 2.1
Name: odoo14-addon-email_template_configurator
Version: 14.0.1.0.2.dev4
Summary: Simplifies use of placeholders in email templates
Home-page: https://github.com/OCA/social
Author: ACSONE SA/NV,Odoo Community Association (OCA)
Author-email: support@odoo-community.org
License: AGPL-3
Classifier: Programming Language :: Python
Classifier: Framework :: Odoo
Classifier: Framework :: Odoo :: 14.0
Classifier: License :: OSI Approved :: GNU Affero General Public License v3
Requires-Python: >=3.6
Requires-Dist: odoo<14.1dev,>=14.0a
